[
	{
		"accountId": 1,
		"individual-discussionId": 1,
		"id": 1
	},
	{
		"accountId": 1,
		"individual-discussionId": 2,
		"id": 2
	},
	{
		"accountId": 1,
		"individual-discussionId": 3,
		"id": 3
	},
	{
		"accountId": 1,
		"individual-discussionId": 4,
		"id": 4
	},
	{
		"accountId": 1,
		"individual-discussionId": 5,
		"id": 5
	},
	{
		"accountId": 1,
		"individual-discussionId": 6,
		"id": 6
	},
	{
		"accountId": 1,
		"individual-discussionId": 7,
		"id": 7
	},
	{
		"accountId": 1,
		"individual-discussionId": 9,
		"id": 8
	},
	{
		"accountId": 1,
		"individual-discussionId": 8,
		"id": 9
	},
	{
		"accountId": 1,
		"individual-discussionId": 9,
		"id": 10
	},
	{
		"accountId": 1,
		"individual-discussionId": 10,
		"id": 11
	},
	{
		"accountId": 1,
		"individual-discussionId": 11,
		"id": 12
	},
	{
		"accountId": 1,
		"individual-discussionId": 12,
		"id": 13
	},
	{
		"accountId": 1,
		"individual-discussionId": 13,
		"id": 14
	},
	{
		"accountId": 1,
		"individual-discussionId": 14,
		"id": 15
	},
	{
		"accountId": 1,
		"individual-discussionId": 24,
		"id": 16
	},
	{
		"accountId": 1,
		"individual-discussionId": 15,
		"id": 17
	},
	{
		"accountId": 1,
		"individual-discussionId": 16,
		"id": 18
	},
	{
		"accountId": 1,
		"individual-discussionId": 17,
		"id": 19
	},
	{
		"accountId": 1,
		"individual-discussionId": 18,
		"id": 20
	}
]